qmrpy/__init__.py
qmrpy/functional.py
qmrpy/_decaes/__init__.py
qmrpy/_decaes/nnls.py
qmrpy/_decaes/surrogate_1d.py
qmrpy/models/__init__.py
qmrpy/models/b1/__init__.py
qmrpy/models/b1/afi.py
qmrpy/models/b1/dam.py
qmrpy/models/noise/__init__.py
qmrpy/models/noise/denoising_mppca.py
qmrpy/models/qsm/__init__.py
qmrpy/models/qsm/gradient_mask.py
qmrpy/models/qsm/pipeline.py
qmrpy/models/qsm/sharp.py
qmrpy/models/qsm/split_bregman.py
qmrpy/models/qsm/unwrap.py
qmrpy/models/qsm/utils.py
qmrpy/models/t1/__init__.py
qmrpy/models/t1/inversion_recovery.py
qmrpy/models/t1/vfa_t1.py
qmrpy/models/t2/__init__.py
qmrpy/models/t2/decaes_t2.py
qmrpy/models/t2/decaes_t2part.py
qmrpy/models/t2/mono_t2.py
qmrpy/models/t2/mwf.py
qmrpy/sim/__init__.py
qmrpy/sim/mrzero.py
qmrpy/sim/noise.py
qmrpy/sim/phantoms.py
qmrpy/sim/simulation.py
THIRD_PARTY_NOTICES.md
qmrpy/py.typed
qmrpy-0.4.0.dist-info/METADATA
qmrpy-0.4.0.dist-info/WHEEL
qmrpy-0.4.0.dist-info/licenses/LICENSE
qmrpy-0.4.0.dist-info/RECORD
