Metadata-Version: 2.4
Name: qmrpy
Version: 0.4.0
Summary: Python implementation (translation) of qMRLab models for quantitative MRI.
Project-URL: Repository, https://github.com/SugimotoKohei/qmrpy
Project-URL: Issues, https://github.com/SugimotoKohei/qmrpy/issues
Author: Kohei Sugimoto
License: MIT
License-File: LICENSE
Keywords: MRI,diffusion,qMRI,qMRLab,relaxometry
Classifier: Development Status :: 2 - Pre-Alpha
Classifier: Intended Audience :: Science/Research
Classifier: License :: OSI Approved :: MIT License
Classifier: Programming Language :: Python :: 3
Classifier: Programming Language :: Python :: 3.11
Classifier: Topic :: Scientific/Engineering :: Medical Science Apps.
Requires-Python: >=3.11
Requires-Dist: mrzerocore>=0.4.1
Requires-Dist: numpy>=1.26
Requires-Dist: pypulseq>=1.4.2.post1
Requires-Dist: scipy>=1.11
Provides-Extra: dev
Requires-Dist: nbclient>=0.10.2; extra == 'dev'
Requires-Dist: nbformat>=5.10.4; extra == 'dev'
Requires-Dist: pytest-cov>=5; extra == 'dev'
Requires-Dist: pytest>=8; extra == 'dev'
Requires-Dist: ruff>=0.6; extra == 'dev'
Provides-Extra: viz
Requires-Dist: pandas>=2.3.3; extra == 'viz'
Requires-Dist: plotnine>=0.13; extra == 'viz'
